pyiron/__init__.py
pyiron/_version.py
pyiron-0.5.2.dist-info/LICENSE
pyiron-0.5.2.dist-info/METADATA
pyiron-0.5.2.dist-info/WHEEL
pyiron-0.5.2.dist-info/top_level.txt
pyiron-0.5.2.dist-info/RECORD
