Metadata-Version: 2.1
Name: pyiron
Version: 0.5.2
Summary: pyiron - an integrated development environment (IDE) for computational materials science.
Home-page: https://github.com/pyiron/pyiron
Author: Max-Planck-Institut für Eisenforschung GmbH - Computational Materials Design (CM) Department
Author-email: janssen@mpie.de
License: BSD
Keywords: pyiron
Classifier: Development Status :: 5 - Production/Stable
Classifier: Topic :: Scientific/Engineering :: Physics
Classifier: License :: OSI Approved :: BSD License
Classifier: Intended Audience :: Science/Research
Classifier: Operating System :: OS Independent
Classifier: Programming Language :: Python :: 3.9
Classifier: Programming Language :: Python :: 3.10
Classifier: Programming Language :: Python :: 3.11
License-File: LICENSE
Requires-Dist: pyiron-atomistics >=0.4.5
